joey/__init__.py
joey/application.py
joey/db.py
joey/cli/__init__.py
joey/cli/utils.py
joey/cli/templates/app/__init__.py
joey/cli/templates/app/models.py
joey/cli/templates/app/routes.py
joey/cli/templates/project/alembic.ini
joey/cli/templates/project/asgi.py
joey/cli/templates/project/migrations/env.py
joey/cli/templates/project/migrations/script.py.mako
joey/cli/templates/project/migrations/versions/.empty
joey/cli/templates/project/settings/__init__.py
joey/cli/templates/project/settings/common.pyt
joey/cli/templates/project/settings/common.yml
joey/cli/templates/project/settings/development.pyt
joey/middleware/__init__.py
joey/middleware/session/__init__.py
joey/middleware/session/middleware.py
joey/middleware/session/backend/__init__.py
joey/middleware/session/backend/base.py
joey/middleware/session/backend/fernet.py
joey/utils/__init__.py
joey/utils/middleware.py
joey/utils/router.py
joey/utils/timezone.py
joey-0.4.0.dist-info/LICENSE
joey-0.4.0.dist-info/METADATA
joey-0.4.0.dist-info/WHEEL
joey-0.4.0.dist-info/entry_points.txt
joey-0.4.0.dist-info/top_level.txt
joey-0.4.0.dist-info/RECORD
